pydantic_ai_stream/__init__.py
pydantic_ai_stream/deps.py
pydantic_ai_stream/py.typed
pydantic_ai_stream/session.py
pydantic_ai_stream/settings.py
pydantic_ai_stream-0.1.1.dist-info/METADATA
pydantic_ai_stream-0.1.1.dist-info/WHEEL
pydantic_ai_stream-0.1.1.dist-info/RECORD
