Metadata-Version: 2.4
Name: pydantic-ai-stream
Version: 0.1.1
Summary: Production runtime for pydantic-ai agents with structured event streaming, session persistence, and cancellation
Project-URL: Homepage, https://github.com/opale-ai/pydantic-ai-stream
Project-URL: Repository, https://github.com/opale-ai/pydantic-ai-stream
Author-email: Opale OSS <oss@opale.ai>
License-Expression: MIT
Keywords: agent,llm,pydantic-ai,redis,streaming
Classifier: Development Status :: 4 - Beta
Classifier: Intended Audience :: Developers
Classifier: License :: OSI Approved :: MIT License
Classifier: Programming Language :: Python :: 3
Classifier: Programming Language :: Python :: 3.11
Classifier: Programming Language :: Python :: 3.12
Classifier: Programming Language :: Python :: 3.13
Classifier: Topic :: Scientific/Engineering :: Artificial Intelligence
Classifier: Typing :: Typed
Requires-Python: >=3.11
Requires-Dist: pydantic-ai>=1.33
Requires-Dist: redis>=5
